{"data":{"wordpressPage":{"title":"Home","content":"<p>One to Grow on is new agriculture podcast that digs into the questions you have about agriculture and tries to understand the impacts of food production.</p>\n","slug":"home","id":"1f7741ea-df9e-5645-9dcc-4faca6bbb8c2","date":"September 26, 2018"},"site":{"id":"Site","siteMetadata":{"title":"On to Grow On","subtitle":"Understanding how food production impacts ourselves and our world"}}},"pageContext":{"isCreatedByStatefulCreatePages":false,"id":"1f7741ea-df9e-5645-9dcc-4faca6bbb8c2"}}